setup.py
distributions_udacity_005aws/Binomialdistribution.py
distributions_udacity_005aws/Gaussiandistribution.py
distributions_udacity_005aws/Generaldistribution.py
distributions_udacity_005aws/__init__.py
distributions_udacity_005aws.egg-info/PKG-INFO
distributions_udacity_005aws.egg-info/SOURCES.txt
distributions_udacity_005aws.egg-info/dependency_links.txt
distributions_udacity_005aws.egg-info/not-zip-safe
distributions_udacity_005aws.egg-info/top_level.txt